chocopearl/__init__.py
chocopearl/corsika.py
chocopearl/datascience.py
chocopearl/dirac.py
chocopearl/general.py
chocopearl/nummath.py
chocopearl/osfunc.py
chocopearl/particle.py
chocopearl/relativity.py
chocopearl/stats.py
chocopearl-1.1.1.dist-info/LICENSE
chocopearl-1.1.1.dist-info/METADATA
chocopearl-1.1.1.dist-info/WHEEL
chocopearl-1.1.1.dist-info/top_level.txt
chocopearl-1.1.1.dist-info/RECORD
