Metadata-Version: 2.1
Name: chocopearl
Version: 1.1.1
Summary: General Purpose/Physics tools
Author: FranciscoLodbrok (Francisco García)
Author-email: <cfgarcia1903@gmail.com>
Keywords: python,physics,general,corsika,astroparticle,numerical methods
Classifier: Development Status :: 2 - Pre-Alpha
Classifier: Intended Audience :: Science/Research
Classifier: Programming Language :: Python :: 3
Classifier: Operating System :: Microsoft :: Windows
License-File: LICENSE
Requires-Dist: numpy
Requires-Dist: pandas
Requires-Dist: plotly
